README.md
setup.py
fair_flow/__init__.py
fair_flow/fair_flow.py
fair_flow.egg-info/PKG-INFO
fair_flow.egg-info/SOURCES.txt
fair_flow.egg-info/dependency_links.txt
fair_flow.egg-info/top_level.txt
tests/__init__.py
tests/fair_flow_test.py