Metadata-Version: 1.1
Name: fair-flow
Version: 0.0.5
Summary: Simple Workflow Library
Home-page: https://fairanswers.com
Author: Joe Fair
Author-email: joe@fairanswers.com
License: UNKNOWN
Platform: UNKNOWN
Classifier: Programming Language :: Python :: 2
Classifier: License :: OSI Approved :: MIT License
Classifier: Operating System :: OS Independent
